netutil/__init__.py
netutil/network_utility_tui.py
netutil_tui-0.1.2.dist-info/METADATA
netutil_tui-0.1.2.dist-info/WHEEL
netutil_tui-0.1.2.dist-info/entry_points.txt
netutil_tui-0.1.2.dist-info/top_level.txt
netutil_tui-0.1.2.dist-info/RECORD
