Metadata-Version: 2.1
Name: netutil-tui
Version: 0.1.2
Summary: A TUI-based network utility for TCP/UDP listen/write operations.
Home-page: https://github.com/avcuenes/tui_socket_listener
Author: Mehmet Enes Avcu
Author-email: your.email@example.com
License: UNKNOWN
Platform: UNKNOWN
Classifier: Programming Language :: Python :: 3
Classifier: License :: OSI Approved :: MIT License
Classifier: Operating System :: OS Independent
Classifier: Environment :: Console :: Curses
Classifier: Topic :: System :: Networking
Classifier: Topic :: Utilities
Requires-Python: >=3.6
